MANIFEST.in
README.txt
setup.py
listmaker/__init__.py
listmaker/childWindows.py
listmaker/contentManager.py
listmaker/contentRow.py
listmaker/entry.py
listmaker/inputManager.py
listmaker/listmaker.py
listmaker/screenManager.py
listmaker/storageManager.py
listmaker.egg-info/PKG-INFO
listmaker.egg-info/SOURCES.txt
listmaker.egg-info/dependency_links.txt
listmaker.egg-info/requires.txt
listmaker.egg-info/top_level.txt
listmaker/samples/sample.lm