Metadata-Version: 1.2
Name: listmaker
Version: 0.1.0
Summary: A utility for managing hierarchical lists
Home-page: http://pypi.python.org/pypi/listmaker_v010/
Author: Vinayak Suley
Author-email: vinayaksuley@gmail.com
License: LICENSE.txt
Platform: UNKNOWN
Requires-Python: >=3
